fuo_qqmusic/__init__.py
fuo_qqmusic/api.py
fuo_qqmusic/consts.py
fuo_qqmusic/excs.py
fuo_qqmusic/login.py
fuo_qqmusic/provider.py
fuo_qqmusic/provider_ui.py
fuo_qqmusic/schemas.py
fuo_qqmusic/assets/icon.svg
fuo_qqmusic-1.0.15.dist-info/METADATA
fuo_qqmusic-1.0.15.dist-info/WHEEL
fuo_qqmusic-1.0.15.dist-info/entry_points.txt
fuo_qqmusic-1.0.15.dist-info/top_level.txt
fuo_qqmusic-1.0.15.dist-info/RECORD
