Metadata-Version: 2.4
Name: fuo_qqmusic
Version: 1.0.15
Summary: feeluown qqmusic plugin
Home-page: https://github.com/feeluown/feeluown-qqmusic
Author: Cosven
Author-email: yinshaowen241@gmail.com
Keywords: feeluown,plugin,qqmusic
Classifier: Development Status :: 3 - Alpha
Classifier: Programming Language :: Python :: 3.5
Classifier: Programming Language :: Python :: 3.6
Classifier: Programming Language :: Python :: 3.7
Classifier: Programming Language :: Python :: 3.8
Classifier: Programming Language :: Python :: 3.9
Classifier: Programming Language :: Python :: 3 :: Only
Requires-Dist: feeluown>=4.1.13
Requires-Dist: requests
Requires-Dist: marshmallow<4.0.0,>=3.0
Dynamic: author
Dynamic: author-email
Dynamic: classifier
Dynamic: home-page
Dynamic: keywords
Dynamic: requires-dist
Dynamic: summary
